<?xml version="1.0"?>
<Node name="root" dt="0.01" gravity="0 0 -9.81">
    <VisualStyle displayFlags="showForceFields showBehaviorModels showVisual showInteractionForceFields" />
    <DefaultAnimationLoop/>

    <!-- Particle animated by reading the state file -->
    <Node name="Particle" bbox="-1 -1 -1 1 1 1" >
        <MechanicalObject name="ParticleMO" template="Rigid" showObject="1" />

        <!-- Read the file: particleGravity.data -->
        <!-- This file is generated by the example scene: WriteState.xml -->
        <ReadState name="StateReader" filename="particleGravity.data" />

        <Node name="Visu">
            <OglModel color="1.000 0.000 0.000" fileMesh="mesh/torus.obj" name="Visual" />
            <RigidMapping input="@.." output="@Visual" />
        </Node>
    </Node>
</Node>